csvw/__init__.py
csvw/__main__.py
csvw/datatypes.py
csvw/db.py
csvw/dsv.py
csvw/dsv_dialects.py
csvw/frictionless.py
csvw/jsonld.py
csvw/metadata.py
csvw/utils.py
csvw-3.7.0.dist-info/LICENSE
csvw-3.7.0.dist-info/METADATA
csvw-3.7.0.dist-info/WHEEL
csvw-3.7.0.dist-info/entry_points.txt
csvw-3.7.0.dist-info/top_level.txt
csvw-3.7.0.dist-info/RECORD
