Metadata-Version: 2.1
Name: csvw
Version: 3.7.0
Summary: Python library to work with CSVW described tabular data
Home-page: https://github.com/cldf/csvw
Author: Robert Forkel
Author-email: robert_forkel@eva.mpg.de
License: Apache 2.0
Project-URL: Bug Tracker, https://github.com/cldf/csvw/issues
Keywords: csv,w3c,tabular-data
Platform: any
Classifier: Development Status :: 5 - Production/Stable
Classifier: Intended Audience :: Developers
Classifier: Intended Audience :: Science/Research
Classifier: Natural Language :: English
Classifier: Operating System :: OS Independent
Classifier: Programming Language :: Python :: 3
Classifier: Programming Language :: Python :: 3.8
Classifier: Programming Language :: Python :: 3.9
Classifier: Programming Language :: Python :: 3.10
Classifier: Programming Language :: Python :: 3.11
Classifier: Programming Language :: Python :: 3.12
Classifier: Programming Language :: Python :: 3.13
Classifier: Programming Language :: Python :: Implementation :: CPython
Classifier: Programming Language :: Python :: Implementation :: PyPy
Classifier: License :: OSI Approved :: Apache Software License
Requires-Python: >=3.8
License-File: LICENSE
Requires-Dist: attrs>=18.1
Requires-Dist: isodate
Requires-Dist: python-dateutil
Requires-Dist: rfc3986<2
Requires-Dist: uritemplate>=3.0.0
Requires-Dist: babel
Requires-Dist: requests
Requires-Dist: language-tags
Requires-Dist: rdflib
Requires-Dist: termcolor
Requires-Dist: jsonschema
Provides-Extra: dev
Requires-Dist: flake8; extra == "dev"
Requires-Dist: wheel; extra == "dev"
Requires-Dist: twine; extra == "dev"
Requires-Dist: build; extra == "dev"
Provides-Extra: test
Requires-Dist: frictionless; extra == "test"
Requires-Dist: pytest>=5; extra == "test"
Requires-Dist: pytest-mock; extra == "test"
Requires-Dist: requests-mock; extra == "test"
Requires-Dist: pytest-cov; extra == "test"
Provides-Extra: docs
Requires-Dist: sphinx<7; extra == "docs"
Requires-Dist: sphinx-autodoc-typehints; extra == "docs"
Requires-Dist: sphinx-rtd-theme; extra == "docs"
